paradoxapi/__init__.py
paradoxapi/common/__init__.py
paradoxapi/common/gateway.py
paradoxapi/common/com/__init__.py
paradoxapi/common/com/datacommon.py
paradoxapi/common/com/pld_data_com.py
paradoxapi/common/com/setting.py
paradoxapi/common/com/sqlhandle.py
paradoxapi/common/com/tips_data_common.py
paradoxapi/examples/PLDDataApi文档.doc
paradoxapi/examples/__init__.py
paradoxapi/examples/get_balance_sheet_fore_annual_data.py
paradoxapi/google/__init__.py
paradoxapi/google/protobuf/__init__.py
paradoxapi/google/protobuf/descriptor.py
paradoxapi/google/protobuf/descriptor_database.py
paradoxapi/google/protobuf/descriptor_pb2.py
paradoxapi/google/protobuf/descriptor_pool.py
paradoxapi/google/protobuf/json_format.py
paradoxapi/google/protobuf/message.py
paradoxapi/google/protobuf/message_factory.py
paradoxapi/google/protobuf/proto_api.h
paradoxapi/google/protobuf/proto_builder.py
paradoxapi/google/protobuf/python_protobuf.h
paradoxapi/google/protobuf/reflection.py
paradoxapi/google/protobuf/service.py
paradoxapi/google/protobuf/service_reflection.py
paradoxapi/google/protobuf/symbol_database.py
paradoxapi/google/protobuf/text_encoding.py
paradoxapi/google/protobuf/text_format.py
paradoxapi/google/protobuf/timestamp_pb2.py
paradoxapi/google/protobuf/compiler/__init__.py
paradoxapi/google/protobuf/internal/__init__.py
paradoxapi/google/protobuf/internal/_parameterized.py
paradoxapi/google/protobuf/internal/any_test.proto
paradoxapi/google/protobuf/internal/api_implementation.cc
paradoxapi/google/protobuf/internal/api_implementation.py
paradoxapi/google/protobuf/internal/containers.py
paradoxapi/google/protobuf/internal/decoder.py
paradoxapi/google/protobuf/internal/descriptor_database_test.py
paradoxapi/google/protobuf/internal/descriptor_pool_test.py
paradoxapi/google/protobuf/internal/descriptor_pool_test1.proto
paradoxapi/google/protobuf/internal/descriptor_pool_test2.proto
paradoxapi/google/protobuf/internal/descriptor_test.py
paradoxapi-1.0.1.2.dist-info/METADATA
paradoxapi-1.0.1.2.dist-info/WHEEL
paradoxapi-1.0.1.2.dist-info/top_level.txt
paradoxapi-1.0.1.2.dist-info/RECORD
